sbpack/__init__.py
sbpack/lib.py
sbpack/pack.py
sbpack/schemadef.py
sbpack/unpack.py
sbpack/version.py
sbpack/noncwl/__init__.py
sbpack/noncwl/constants.py
sbpack/noncwl/copy.py
sbpack/noncwl/copy_app.py
sbpack/noncwl/manifest.py
sbpack/noncwl/nextflow.py
sbpack/noncwl/utils.py
sbpack/noncwl/wdl.py
sbpack/noncwl/wrapper.py
sbpack/noncwl/js/sample_sheet_generator.js
sbpack/noncwl/js/sample_sheet_switch.js
sbpack/noncwl/js_templates/sample_sheet_generator.js
sbpack/noncwl/js_templates/sample_sheet_switch.js
sbpack-2024.12.17.dist-info/LICENSE
sbpack-2024.12.17.dist-info/METADATA
sbpack-2024.12.17.dist-info/WHEEL
sbpack-2024.12.17.dist-info/entry_points.txt
sbpack-2024.12.17.dist-info/top_level.txt
sbpack-2024.12.17.dist-info/RECORD
