Metadata-Version: 2.1
Name: sbpack
Version: 2024.12.17
Summary: Command line tool to upload and download CWL to and from SB powered platforms.
Home-page: UNKNOWN
Author: Seven Bridges
Author-email: pavle.marinkovic@velsera.com
Maintainer: Seven Bridges
Maintainer-email: pavle.marinkovic@velsera.com
License: UNKNOWN
Keywords: seven bridges cwl common workflow language
Platform: POSIX
Platform: MacOS
Platform: Windows
Classifier: Development Status :: 3 - Alpha
Classifier: Intended Audience :: Developers
Classifier: License :: OSI Approved :: Apache Software License
Classifier: Natural Language :: English
Classifier: Operating System :: POSIX
Classifier: Programming Language :: Python :: 3.7
Classifier: Programming Language :: Python :: 3.8
Classifier: Programming Language :: Python :: 3.9
Classifier: Programming Language :: Python :: 3.10
Classifier: Programming Language :: Python :: 3 :: Only
Requires-Python: >=3.7
License-File: LICENSE
Requires-Dist: ruamel.yaml (>=0.16)
Requires-Dist: sevenbridges-python (>=2.0)
Requires-Dist: nf-core (==2.1)
Requires-Dist: wrabbit (==0.3.0)
Requires-Dist: pillow (>=11.0.0)
